{
    "documents": [        
         {
            "author": "서울아산병원",
            "datetime": "2014-05-02T10:56:13.000+09:00",
            "play_time": 245,
            "thumbnail": "https://search4.kakaocdn.net/argon/138x78_80_pr/IEsw4uZ4UMv",
            "title": "사무실에서 하는 허리 스트레칭",
            "url": "http://www.youtube.com/watch?v=-JzaMksAeew"
        },
        
        {
            "author": "미유탱Miu_Taeng",
            "datetime": "2021-02-07T14:24:02.000+09:00",
            "play_time": 302,
            "thumbnail": "https://search3.kakaocdn.net/argon/138x78_80_pr/6LEZ8bwaMaw",
            "title": "혼자 뭐하게? 허리 아파서 스트레칭 중...",
            "url": "http://www.youtube.com/watch?v=1rd4PdL7uMU"
        },
        
        {
            "author": "다빈이(경기도 안산)",
            "datetime": "2021-06-18T18:26:02.000+09:00",
            "play_time": 140,
            "thumbnail": "https://search1.kakaocdn.net/argon/138x78_80_pr/LTgQUE3FJjw",
            "title": "골반 & 허리/스트레칭",
            "url": "http://tvpot.daum.net/v/rv7huvf3vuf9mwk1va0akjld4"
        },        
        {
            "author": "야핏 YAFIT",
            "datetime": "2019-05-26T11:45:00.000+09:00",
            "play_time": 382,
            "thumbnail": "https://search2.kakaocdn.net/argon/138x78_80_pr/5tfGvXJLXBF",
            "title": "[02_허리통증 스트레칭] 현직 한의사가 알려주는 허리스트레칭 3가지만 기억하세요!ㅣ한의사 박용환",
            "url": "http://www.youtube.com/watch?v=N5Yfxq7AK0I"
        },
        {
            "author": "Master Choi",
            "datetime": "2021-03-29T08:00:12.000+09:00",
            "play_time": 357,
            "thumbnail": "https://search4.kakaocdn.net/argon/138x78_80_pr/DVwACB8FWrt",
            "title": "대부분 잘 못 하고 있는 허리 유연성 스트레칭, 이 영상 먼저 보고 하세요! | 장인비법서 With 마스터 최 | 에피소드 12",
            "url": "http://www.youtube.com/watch?v=gGIL-r6g0ac"
        } 
      ]
}